{"title":"¿Cuánto tiempo falta?","subtitle":"","data":[{"name":"oda-instruccion","attr":{"class":""},"content":"Marca así fxemoji:crossmark la imagen que represente la actividad que tardará más tiempo en realizarse.","id":"03fb78b63","location":"0"},{"name":"util-text","attr":{"design":"0","class":" px-3 text-xl"},"content":"a) ¿Quién tardará más aseándose?","id":"142735671","location":"1"},{"name":"layout-grid","attr":{"columns":1,"columns-md":3,"gap":"5","class":" px-3 my-5"},"content":[{"name":"module-check","attr":{"v-bind":"{options:['fxemoji:crossmark'],answer:0}","float":"topleft","class":""},"content":[{"name":"layout-img","attr":{"img":"https://ucarecdn.com/12e5ca8d-79fc-4147-96a5-b5f55eb65cc0/","class":""},"content":[],"id":"0ee1842a7","location":"2,0,0"}],"id":"0ec6d6622","location":"2,0"},{"name":"module-check","attr":{"v-bind":"{options:['fxemoji:crossmark'],answer:0}","float":"topleft","class":""},"content":[{"name":"layout-img","attr":{"img":"https://ucarecdn.com/11a2ee6a-c62e-43c2-ad98-2bee4d741d4e/","class":""},"content":[],"id":"0ee1842a7","location":"2,1,0"}],"id":"64ad21c1","location":"2,1"},{"name":"module-check","attr":{"v-bind":"{options:['fxemoji:crossmark'],answer:1}","float":"topleft","class":""},"content":[{"name":"layout-img","attr":{"img":"https://ucarecdn.com/b877058b-da30-4da0-8657-c9558896fd40/","class":""},"content":[],"id":"0ee1842a7","location":"2,2,0"}],"id":"3843c8df","location":"2,2"}],"id":"2b19f5af4","location":"2"},{"name":"util-text","attr":{"design":"0","class":" px-3 text-xl"},"content":"b) ¿Qué alimento tomará más tiempo comerse?","id":"82156f1a","location":"3"},{"name":"layout-grid","attr":{"columns":1,"columns-md":3,"gap":"5","class":" px-3 my-5"},"content":[{"name":"module-check","attr":{"v-bind":"{options:['fxemoji:crossmark'],answer:0}","float":"topleft","class":""},"content":[{"name":"layout-img","attr":{"img":"https://ucarecdn.com/5b8e1faa-49fb-407e-b022-87810a3d8307/","class":""},"content":[],"id":"0ee1842a7","location":"4,0,0"}],"id":"0ec6d6622","location":"4,0"},{"name":"module-check","attr":{"v-bind":"{options:['fxemoji:crossmark'],answer:0}","float":"topleft","class":""},"content":[{"name":"layout-img","attr":{"img":"https://ucarecdn.com/99113221-9d0c-408a-9580-8b491237d2a1/","class":""},"content":[],"id":"0ee1842a7","location":"4,1,0"}],"id":"64ad21c1","location":"4,1"},{"name":"module-check","attr":{"v-bind":"{options:['fxemoji:crossmark'],answer:1}","float":"topleft","class":""},"content":[{"name":"layout-img","attr":{"img":"https://ucarecdn.com/dc581006-c8db-4d6f-8315-bbe8d2539cba/","class":""},"content":[],"id":"0ee1842a7","location":"4,2,0"}],"id":"3843c8df","location":"4,2"}],"id":"ab4395f8","location":"4"},{"name":"util-text","attr":{"design":"0","class":" px-3 text-xl"},"content":"c) ¿Quién tardará más en llegar al final de la resbaladilla?","id":"f1838c3f","location":"5"},{"name":"layout-grid","attr":{"columns":1,"columns-md":3,"gap":"5","class":" px-3 my-5"},"content":[{"name":"module-check","attr":{"v-bind":"{options:['fxemoji:crossmark'],answer:1}","float":"topleft","class":""},"content":[{"name":"layout-img","attr":{"img":"https://ucarecdn.com/27ec1f7d-613a-4789-92ca-842aa20a1f42/","class":""},"content":[],"id":"0ee1842a7","location":"6,0,0"}],"id":"0ec6d6622","location":"6,0"},{"name":"module-check","attr":{"v-bind":"{options:['fxemoji:crossmark'],answer:0}","float":"topleft","class":""},"content":[{"name":"layout-img","attr":{"img":"https://ucarecdn.com/1736296b-f24c-45fa-b3bd-7d08bbc87dcf/","class":""},"content":[],"id":"0ee1842a7","location":"6,1,0"}],"id":"64ad21c1","location":"6,1"},{"name":"module-check","attr":{"v-bind":"{options:['fxemoji:crossmark'],answer:0}","float":"topleft","class":""},"content":[{"name":"layout-img","attr":{"img":"https://ucarecdn.com/b55b4a3e-b82e-4727-bdc3-f762153b88bc/","class":""},"content":[],"id":"0ee1842a7","location":"6,2,0"}],"id":"3843c8df","location":"6,2"}],"id":"56452c52","location":"6"}],"view":false,"version":"0.11","loaderVersion":"v1.0.15","loader":"https://cdn.jsdelivr.net/gh/bluemx/blueodasv2@v1.0.15/basicas/assets/loader.min.js","mediafiles":[{"name":"5.png","uuid":"99113221-9d0c-408a-9580-8b491237d2a1","cdn":"https://ucarecdn.com/99113221-9d0c-408a-9580-8b491237d2a1/"},{"name":"4.png","uuid":"5b8e1faa-49fb-407e-b022-87810a3d8307","cdn":"https://ucarecdn.com/5b8e1faa-49fb-407e-b022-87810a3d8307/"},{"name":"2.png","uuid":"11a2ee6a-c62e-43c2-ad98-2bee4d741d4e","cdn":"https://ucarecdn.com/11a2ee6a-c62e-43c2-ad98-2bee4d741d4e/"},{"name":"3.png","uuid":"b877058b-da30-4da0-8657-c9558896fd40","cdn":"https://ucarecdn.com/b877058b-da30-4da0-8657-c9558896fd40/"},{"name":"6.png","uuid":"dc581006-c8db-4d6f-8315-bbe8d2539cba","cdn":"https://ucarecdn.com/dc581006-c8db-4d6f-8315-bbe8d2539cba/"},{"name":"1.png","uuid":"12e5ca8d-79fc-4147-96a5-b5f55eb65cc0","cdn":"https://ucarecdn.com/12e5ca8d-79fc-4147-96a5-b5f55eb65cc0/"},{"name":"9.png","uuid":"b55b4a3e-b82e-4727-bdc3-f762153b88bc","cdn":"https://ucarecdn.com/b55b4a3e-b82e-4727-bdc3-f762153b88bc/"},{"name":"8.png","uuid":"1736296b-f24c-45fa-b3bd-7d08bbc87dcf","cdn":"https://ucarecdn.com/1736296b-f24c-45fa-b3bd-7d08bbc87dcf/"},{"name":"7.png","uuid":"27ec1f7d-613a-4789-92ca-842aa20a1f42","cdn":"https://ucarecdn.com/27ec1f7d-613a-4789-92ca-842aa20a1f42/"}]}