{"title":"Depende del ángulo del que se mire","subtitle":"","data":[{"name":"oda-instruccion","minimize":false,"attr":{"class":""},"content":"Arrastra el ejemplo de ángulo al tipo de ángulo que se solicita. Después contesta las preguntas.\n","id":"2d56dbafa","location":"0"},{"name":"div","minimize":false,"attr":{"class":" flex flex-wrap justify-center items-center"},"content":[{"name":"div","minimize":false,"attr":{"class":" m-5 justify-center items-center w-52"},"content":[{"name":"layout-box","minimize":false,"attr":{"img":"","design":"","class":" font-bold w-52 h-8 text-white bg-isok !rounded-none"},"content":"90°","id":"0f766aea0","location":"1,0,0"},{"name":"module-drop","minimize":false,"attr":{"name":"drop1","design":1,"answer":"a","class":" w-52 h-52"},"content":[],"id":"1c51d7a46","location":"1,0,1"},{"name":"util-text","minimize":false,"attr":{"design":"0","class":" text-center"},"content":"¿Cómo se les llama\na estos ángulos?","id":"20e62f9ab","location":"1,0,2"},{"name":"module-drop","minimize":false,"attr":{"name":"drop1","design":1,"answer":"aa","class":" w-52 h-12"},"content":[],"id":"96e3901c","location":"1,0,3"}],"id":"3b714977","location":"1,0"},{"name":"div","minimize":false,"attr":{"class":" m-5 justify-center items-center w-52"},"content":[{"name":"layout-box","minimize":false,"attr":{"img":"","design":"","class":" font-bold w-52 h-8 text-white bg-clear !rounded-none"},"content":"40°","id":"0f766aea0","location":"1,1,0"},{"name":"module-drop","minimize":false,"attr":{"name":"drop1","design":1,"answer":"b","class":" w-52 h-52"},"content":[],"id":"1c51d7a46","location":"1,1,1"},{"name":"util-text","minimize":false,"attr":{"design":"0","class":" text-center"},"content":"¿Cómo se les llama\na estos ángulos?","id":"20e62f9ab","location":"1,1,2"},{"name":"module-drop","minimize":false,"attr":{"name":"drop1","design":1,"answer":"bb","class":" w-52 h-12"},"content":[],"id":"96e3901c","location":"1,1,3"}],"id":"b1a16994","location":"1,1"},{"name":"div","minimize":false,"attr":{"class":" m-5 justify-center items-center w-52"},"content":[{"name":"layout-box","minimize":false,"attr":{"img":"","design":"","class":" font-bold w-52 h-8 text-white bg-main !rounded-none"},"content":"110°","id":"0f766aea0","location":"1,2,0"},{"name":"module-drop","minimize":false,"attr":{"name":"drop1","design":1,"answer":"c","class":" w-52 h-52"},"content":[],"id":"1c51d7a46","location":"1,2,1"},{"name":"util-text","minimize":false,"attr":{"design":"0","class":" text-center"},"content":"¿Cómo se les llama\na estos ángulos?","id":"20e62f9ab","location":"1,2,2"},{"name":"module-drop","minimize":false,"attr":{"name":"drop1","design":1,"answer":"cc","class":" w-52 h-12"},"content":[],"id":"96e3901c","location":"1,2,3"}],"id":"db299ada","location":"1,2"}],"id":"2b700867e","location":"1"},{"name":"div","minimize":false,"attr":{"class":" justify-center items-center flex flex-wrap rounded-xl bg-pastel3"},"content":[{"name":"module-drag","minimize":false,"attr":{"v-bind:allok":false,"dropzone":"drop1","answer":"b","liner":0,"connector":0,"design":"","class":" m-5 w-52 h-52 bg-pastel6"},"content":[{"name":"layout-img","minimize":false,"attr":{"v-bind:img-variable":"","img":"https://ucarecdn.com/6287be9f-56d9-48e6-a3f9-24c975aa0bc9/","class":" w-full h-full"},"content":[],"id":"0b365fae2","location":"2,0,0"}],"id":"72e32094","location":"2,0"},{"name":"module-drag","minimize":false,"attr":{"v-bind:allok":false,"dropzone":"drop1","answer":"c","liner":0,"connector":0,"design":"","class":" m-5 w-52 h-52 bg-pastel6"},"content":[{"name":"layout-img","minimize":false,"attr":{"v-bind:img-variable":"","img":"https://ucarecdn.com/bbed4328-7626-4f19-b9f3-b7e9fac20407/","class":" w-full h-full"},"content":[],"id":"0b365fae2","location":"2,1,0"}],"id":"707af0e1","location":"2,1"},{"name":"module-drag","minimize":false,"attr":{"v-bind:allok":false,"dropzone":"drop1","answer":"a","liner":0,"connector":0,"design":"","class":" m-5 w-52 h-52 bg-pastel6"},"content":[{"name":"layout-img","minimize":false,"attr":{"v-bind:img-variable":"","img":"https://ucarecdn.com/e705a3f0-db32-478d-a0ff-637e75fb527f/","class":" w-full h-full"},"content":[],"id":"0b365fae2","location":"2,2,0"}],"id":"0fbfcc3bb","location":"2,2"}],"id":"Drags","location":"2"},{"name":"div","minimize":false,"attr":{"class":" mt-5 justify-center items-center flex flex-wrap rounded-xl bg-pastel3"},"content":[{"name":"module-drag","minimize":false,"attr":{"v-bind:allok":false,"dropzone":"drop1","answer":"cc","liner":0,"connector":0,"design":"","class":" m-5 rounded-xl w-52 h-12 bg-sec"},"content":[{"name":"layout-box","minimize":false,"attr":{"img":"","design":"","class":" text-md font-bold rounded-xl w-full h-full text-white"},"content":"Ángulos \nobtusos.","id":"0a6deb915","location":"3,0,0"}],"id":"13812923","location":"3,0"},{"name":"module-drag","minimize":false,"attr":{"v-bind:allok":false,"dropzone":"drop1","answer":"bb","liner":0,"connector":0,"design":"","class":" m-5 rounded-xl w-52 h-12 bg-sec"},"content":[{"name":"layout-box","minimize":false,"attr":{"img":"","design":"","class":" text-md font-bold rounded-xl w-full h-full text-white"},"content":"Ángulos \nagudos.","id":"0a6deb915","location":"3,1,0"}],"id":"21ce3bc2","location":"3,1"},{"name":"module-drag","minimize":false,"attr":{"v-bind:allok":false,"dropzone":"drop1","answer":"aa","liner":0,"connector":0,"design":"","class":" m-5 rounded-xl w-52 h-12 bg-sec"},"content":[{"name":"layout-box","minimize":false,"attr":{"img":"","design":"","class":" text-md font-bold rounded-xl w-full h-full text-white"},"content":"Ángulos rectos.","id":"0a6deb915","location":"3,2,0"}],"id":"72e32094","location":"3,2"}],"id":"7a679eb4","location":"3"}],"view":false,"version":"0.16","loaderVersion":"v1.0.23","loader":"https://cdn.jsdelivr.net/gh/bluemx/blueodasv2@v1.1.0/lib/loader.min.js","mediafiles":[{"name":"02.png","uuid":"6287be9f-56d9-48e6-a3f9-24c975aa0bc9","cdn":"https://ucarecdn.com/6287be9f-56d9-48e6-a3f9-24c975aa0bc9/"},{"name":"03.png","uuid":"bbed4328-7626-4f19-b9f3-b7e9fac20407","cdn":"https://ucarecdn.com/bbed4328-7626-4f19-b9f3-b7e9fac20407/"},{"name":"01.png","uuid":"e705a3f0-db32-478d-a0ff-637e75fb527f","cdn":"https://ucarecdn.com/e705a3f0-db32-478d-a0ff-637e75fb527f/"}]}